Workbook

Sheet Charts
T3: Banking (35% profitability- 35% risk - 15% growth) | W3: Consumer Durables (40% profitability - 30% growth - 20% ) | Z3: Automobile (35% profitability - 30% growth - 20% P/E)
T5: ROE | U5: ● 11.7% | W5: ROE | X5: ● 13.3% | Z5: ROE | AA5: ● 11.7%
T6: ROCE | U6: ● 11.7% | W6: ROCE | X6: ● 13.3% | Z6: ROCE | AA6: ● 11.7%
T7: EPS | U7: ● 11.7% | W7: EPS | X7: ● 13.3% | Z7: EPS | AA7: ● 11.7%
T8: P/E Ratio | U8: ● 20.0% | W8: P/E Ratio | X8: ● 20.0% | Z8: P/E Ratio | AA8: ● 20.0%
T9: D/E | U9: ● 15.0% | W9: D/E | X9: ● 5.0% | Z9: D/E | AA9: ● 7.5%
T10: Return 3Y | U10: ● 5.0% | W10: Return 3Y | X10: ● 10.0% | Z10: Return 3Y | AA10: ● 10.0%
T11: Sales Gr 3Y | U11: ● 5.0% | W11: Sales Gr 3Y | X11: ● 10.0% | Z11: Sales Gr 3Y | AA11: ● 10.0%
T12: Profit Gr 3Y | U12: ● 5.0% | W12: Profit Gr 3Y | X12: ● 10.0% | Z12: Profit Gr 3Y | AA12: ● 10.0%
T13: ICR | U13: ● 15.0% | W13: ICR | X13: ● 5.0% | Z13: ICR | AA13: ● 7.5.0%

Sheet Tables
A1: Stocks | B1: Con.D | C1: Banking | D1: Auto.M | F1: Stocks | G1: ROE % | H1: ROCE %
A2: Blue Star | B2: 77.159193 | F2: Blue Star | G2: =VLOOKUP(F2,'[1]Con. D'!A1:U8,2,0) -> 20.62 | H2: =VLOOKUP(F2,'[1]Con. D'!A1:E8,4,0) -> 26.2
A3: Force Motors | D3: 69.381759 | F3: Force Motors | G3: =VLOOKUP(F3,'[1]Auto. M'!A1:E8,3,0) -> 4.5506265 | H3: =VLOOKUP(F3,'[1]Auto. M'!A1:E8,4,0) -> 29.8 | J3: Sector | K3: Avg | L3: highest
A4: Kotak Mah. Bank | C4: 65.45 | F4: Kotak Mah. Bank | G4: =VLOOKUP(F4,[1]Banking!A1:E8,2,0) -> 15.37 | H4: =VLOOKUP(F4,[1]Banking!A1:E8,4,0) -> 8.17 | J4: Con.D | K4: 49.36783 | L4: 77.159193
A5: IDBI Bank | C5: 54.22 | F5: IDBI Bank | G5: =VLOOKUP(F5,[1]Banking!A1:E8,2,0) -> 13.55 | H5: =VLOOKUP(F5,[1]Banking!A1:E8,4,0) -> 6.78 | J5: Banking | K5: 46.72576 | L5: 65.441784
A6: ICICI Bank | C6: 53.59 | F6: ICICI Bank | G6: =VLOOKUP(F6,[1]Banking!A1:E8,2,0) -> 17.97 | H6: =VLOOKUP(F6,[1]Banking!A1:E8,4,0) -> 7.88 | J6: Auto. M | K6: 43.944046 | L6: 49.61964
A7: Havells India | B7: 50.649841 | F7: Havells India | G7: =VLOOKUP(F7,'[1]Con. D'!A1:F8,3,0) -> 11.180758 | H7: =VLOOKUP(F7,'[1]Con. D'!A1:E8,4,0) -> 25.32
A8: Bajaj Auto | D8: 49.61964 | F8: Bajaj Auto | G8: =VLOOKUP(F8,'[1]Auto. M'!A1:E8,2,0) -> 22.77 | H8: =VLOOKUP(F8,'[1]Auto. M'!A1:E8,4,0) -> 22.77
A9: Tata Motors | D9: 48.215869 | F9: Tata Motors | G9: =VLOOKUP(F9,'[1]Auto. M'!A1:E8,2,0) -> 28.08 | H9: =VLOOKUP(F9,'[1]Auto. M'!A1:E8,4,0) -> 19.97
A10: Voltas | B10: 47.775487 | F10: Voltas | G10: =VLOOKUP(F10,'[1]Con. D'!A1:E8,2,0) -> 13.35 | H10: =VLOOKUP(F10,'[1]Con. D'!A1:E8,4,0) -> 17.64
A12: Stocks | B12: Con.D | C12: Banking | D12: Auto.M | F12: Stocks | G12: 3Y Return % | H12: Profit Gr 3Y %
A13: Blue Star | B13: =VLOOKUP(A13,'[1]Con. D'!A1:K8,10,0) -> 0.12 | F13: Blue Star | G13: =VLOOKUP(F13,'[1]Con. D'!A1:S8,14,0) -> 52.42 | H13: =VLOOKUP(F13,'[1]Con. D'!A1:S8,18,0) -> 52.09
A14: Havells India | B14: =VLOOKUP(A14,'[1]Con. D'!A2:K9,10,0) -> 0.04 | F14: Havells India | G14: =VLOOKUP(F14,'[1]Con. D'!A2:S9,14,0) -> 8.17 | H14: =VLOOKUP(F14,'[1]Con. D'!A2:S9,18,0) -> 7.37
A15: Voltas | B15: =VLOOKUP(A15,'[1]Con. D'!A3:K10,10,0) -> 0.14 | F15: Voltas | G15: =VLOOKUP(F15,'[1]Con. D'!A3:S10,14,0) -> 10.37 | H15: =VLOOKUP(F15,'[1]Con. D'!A3:S10,18,0) -> 17.71
A16: Kotak Mah. Bank | C16: =VLOOKUP(A16,[1]Banking!A1:K9,10,0) -> 3.76 | F16: Kotak Mah. Bank | G16: =VLOOKUP(F16,[1]Banking!A1:S8,14,0) -> 6.06 | H16: =VLOOKUP(F16,[1]Banking!A1:S8,18,0) -> 22.32
A17: ICICI Bank | C17: =VLOOKUP(A17,[1]Banking!A2:K10,10,0) -> 5.97 | F17: ICICI Bank | G17: =VLOOKUP(F17,[1]Banking!A2:S9,14,0) -> 22.81 | H17: =VLOOKUP(F17,[1]Banking!A2:S9,18,0) -> 26.67
A18: IDBI Bank | C18: =VLOOKUP(A18,[1]Banking!A3:K11,10,0) -> 5.35 | F18: IDBI Bank | G18: =VLOOKUP(F18,[1]Banking!A3:S10,14,0) -> 40.08 | H18: =VLOOKUP(F18,[1]Banking!A3:S10,18,0) -> 44.43
A19: Force Motors | D19: =VLOOKUP(A19,'[1]Auto. M'!A1:K8,10,0) -> 0.01 | F19: Force Motors | G19: =VLOOKUP(F19,'[1]Auto. M'!A1:S8,14,0) -> 163.27 | H19: =VLOOKUP(F19,'[1]Auto. M'!A1:S8,18,0) -> 99.69
A20: Tata Motors | D20: =VLOOKUP(A20,'[1]Auto. M'!A2:K9,10,0) -> 0.62 | F20: Tata Motors | G20: =VLOOKUP(F20,'[1]Auto. M'!A2:S9,14,0) -> 15.93 | H20: =VLOOKUP(F20,'[1]Auto. M'!A2:S9,18,0) -> 65.49
A21: Bajaj Auto | D21: =VLOOKUP(A21,'[1]Auto. M'!A3:K10,10,0) -> 0.27 | F21: Bajaj Auto | G21: =VLOOKUP(F21,'[1]Auto. M'!A3:S10,14,0) -> 27.26 | H21: =VLOOKUP(F21,'[1]Auto. M'!A3:S10,18,0) -> 10.38

Sheet Con. D
A1: Stocks | B1: ROE ratio | C1: Weightage | D1: ROCE (%) | E1: Weightage | F1: EPS | G1: Weightage | H1: P/E Ratio | I1: Weightage | J1: Debt to Equity | K1: Weightage | L1: Interest Coverage Ratio | M1: Weightage | N1: Return over 3Y (%) | O1: Weightage | P1: Sales Growth 3Y (%) | Q1: Weightage | R1: Profit Growth 3Y (%) | S1: Weightage | T1: Total Score (Weighted) | U1: Final Rank
A2: Weightage | B2: 40 | H2: 20 | J2: 10 | N2: 30
A3: Metrics | B3: 13.33 | D3: 13.33 | F3: 13.34 | H3: 20 | J3: 5 | L3: 5 | N3: 10 | P3: 10 | R3: 10
A4: Voltas | B4: =VLOOKUP(A4,Data2!B1:O28,14,FALSE) -> 13.35 | C4: =(B4 - MIN($B$4:$B$8)) / (MAX($B$4:$B$8) - MIN($B$4:$B$8))*$B$3 -> 4.7917533 | D4: =VLOOKUP(A4,Data2!B1:R29,10,FALSE) -> 17.64 | E4: =(D4 - MIN($D$4:$D$8)) / (MAX($D$4:$D$8) - MIN($D$4:$D$8))*$D$3 -> 4.6922407 | F4: =VLOOKUP(A4,Data2!B1:R29,11,FALSE) -> 25.43 | G4: =(F4 - MIN($F$4:$F$8)) / (MAX($F$4:$F$8) - MIN($F$4:$F$8))*$F$3 -> 11.137673 | H4: =VLOOKUP(A4,Data2!B1:R29,3,FALSE) -> 54.95 | I4: =(MAX($H$4:$H$8) - H4) / (MAX($H$4:$H$8) - MIN($H$4:$H$8))*$H$3 -> 9.8005884 | J4: =VLOOKUP(A4,Data2!B1:R29,12,FALSE) -> 0.14 | K4: =(MAX($J$4:$J$8) - J4) / (MAX($J$4:$J$8) - MIN($J$4:$J$8))*$J$3 -> 0 | L4: =VLOOKUP(A4,Data2!B1:R29,13,FALSE) -> 19.92 | M4: =(L4 - MIN($L$4:$L$8)) / (MAX($L$4:$L$8) - MIN($L$4:$L$8))*$L$3 -> 1.2480834 | N4: =VLOOKUP(A4,Data2!B1:S29,18,FALSE) -> 10.37 | O4: =(N4 - MIN($N$4:$N$8)) / (MAX($N$4:$N$8) - MIN($N$4:$N$8))*$N$3 -> 2.8668363 | P4: =VLOOKUP(A4,Data2!B1:R29,15,FALSE) -> 24.77 | Q4: =(P4 - MIN($P$4:$P$8)) / (MAX($P$4:$P$8) - MIN($P$4:$P$8))*$P$3 -> 9.6096984 | R4: =VLOOKUP(A4,Data2!B1:R29,16,FALSE) -> 17.71 | S4: =(R4 - MIN($R$4:$R$8)) / (MAX($R$4:$R$8) - MIN($R$4:$R$8))*$R$3 -> 3.6286138 | T4: =SUM(C4+E4+G4+I4+K4+M4+O4+Q4+S4) -> 47.775487 | U4: =RANK(T4,$T$4:$T$8,0) -> 3
A5: Havells India | B5: =VLOOKUP(A5,Data2!B2:O29,14,FALSE) -> 18.79 | C5: =(B5 - MIN($B$4:$B$8)) / (MAX($B$4:$B$8) - MIN($B$4:$B$8))*$B$3 -> 11.180758 | D5: =VLOOKUP(A5,Data2!B2:R30,10,FALSE) -> 25.32 | E5: =(D5 - MIN($D$4:$D$8)) / (MAX($D$4:$D$8) - MIN($D$4:$D$8))*$D$3 -> 12.442006 | F5: =VLOOKUP(A5,Data2!B2:R30,11,FALSE) -> 22.52 | G5: =(F5 - MIN($F$4:$F$8)) / (MAX($F$4:$F$8) - MIN($F$4:$F$8))*$F$3 -> 9.2073197 | H5: =VLOOKUP(A5,Data2!B2:R30,3,FALSE) -> 69.94 | I5: =(MAX($H$4:$H$8) - H5) / (MAX($H$4:$H$8) - MIN($H$4:$H$8))*$H$3 -> 0 | J5: =VLOOKUP(A5,Data2!B2:R30,12,FALSE) -> 0.04 | K5: =(MAX($J$4:$J$8) - J5) / (MAX($J$4:$J$8) - MIN($J$4:$J$8))*$J$3 -> 4.1666667 | L5: =VLOOKUP(A5,Data2!B2:R30,13,FALSE) -> 44.39 | M5: =(L5 - MIN($L$4:$L$8)) / (MAX($L$4:$L$8) - MIN($L$4:$L$8))*$L$3 -> 5 | N5: =VLOOKUP(A5,Data2!B2:S30,18,FALSE) -> 8.17 | O5: =(N5 - MIN($N$4:$N$8)) / (MAX($N$4:$N$8) - MIN($N$4:$N$8))*$N$3 -> 2.4936387 | P5: =VLOOKUP(A5,Data2!B2:R30,15,FALSE) -> 16.04 | Q5: =(P5 - MIN($P$4:$P$8)) / (MAX($P$4:$P$8) - MIN($P$4:$P$8))*$P$3 -> 4.4470727 | R5: =VLOOKUP(A5,Data2!B2:R30,16,FALSE) -> 7.37 | S5: =(R5 - MIN($R$4:$R$8)) / (MAX($R$4:$R$8) - MIN($R$4:$R$8))*$R$3 -> 1.7123795 | T5: =SUM(C5+E5+G5+I5+K5+M5+O5+Q5+S5) -> 50.649841 | U5: =RANK(T5,$T$4:$T$8,0) -> 2
A6: Crompton Gr. Con | B6: =VLOOKUP(A6,Data2!B3:O30,14,FALSE) -> 17.4 | C6: =(B6 - MIN($B$4:$B$8)) / (MAX($B$4:$B$8) - MIN($B$4:$B$8))*$B$3 -> 9.5482731 | D6: =VLOOKUP(A6,Data2!B3:R31,10,FALSE) -> 19.01 | E6: =(D6 - MIN($D$4:$D$8)) / (MAX($D$4:$D$8) - MIN($D$4:$D$8))*$D$3 -> 6.0746858 | F6: =VLOOKUP(A6,Data2!B3:R31,11,FALSE) -> 8.64 | G6: =(F6 - MIN($F$4:$F$8)) / (MAX($F$4:$F$8) - MIN($F$4:$F$8))*$F$3 -> 0 | H6: =VLOOKUP(A6,Data2!B3:R31,3,FALSE) -> 39.35 | I6: =(MAX($H$4:$H$8) - H6) / (MAX($H$4:$H$8) - MIN($H$4:$H$8))*$H$3 -> 20 | J6: =VLOOKUP(A6,Data2!B3:R31,12,FALSE) -> 0.14 | K6: =(MAX($J$4:$J$8) - J6) / (MAX($J$4:$J$8) - MIN($J$4:$J$8))*$J$3 -> 0 | L6: =VLOOKUP(A6,Data2!B3:R31,13,FALSE) -> 16.76 | M6: =(L6 - MIN($L$4:$L$8)) / (MAX($L$4:$L$8) - MIN($L$4:$L$8))*$L$3 -> 0.76356946 | N6: =VLOOKUP(A6,Data2!B3:S31,18,FALSE) -> -3.78 | O6: =(N6 - MIN($N$4:$N$8)) / (MAX($N$4:$N$8) - MIN($N$4:$N$8))*$N$3 -> 0.46649703 | P6: =VLOOKUP(A6,Data2!B3:R31,15,FALSE) -> 13.39 | Q6: =(P6 - MIN($P$4:$P$8)) / (MAX($P$4:$P$8) - MIN($P$4:$P$8))*$P$3 -> 2.8799527 | R6: =VLOOKUP(A6,Data2!B3:R31,16,FALSE) -> -1.87 | S6: =(R6 - MIN($R$4:$R$8)) / (MAX($R$4:$R$8) - MIN($R$4:$R$8))*$R$3 -> 0 | T6: =SUM(C6+E6+G6+I6+K6+M6+O6+Q6+S6) -> 39.732978 | U6: =RANK(T6,$T$4:$T$8,0) -> 4
A7: Whirlpool India | B7: =VLOOKUP(A7,Data2!B4:O31,14,FALSE) -> 9.27 | C7: =(B7 - MIN($B$4:$B$8)) / (MAX($B$4:$B$8) - MIN($B$4:$B$8))*$B$3 -> 0 | D7: =VLOOKUP(A7,Data2!B4:R32,10,FALSE) -> 12.99 | E7: =(D7 - MIN($D$4:$D$8)) / (MAX($D$4:$D$8) - MIN($D$4:$D$8))*$D$3 -> 0 | F7: =VLOOKUP(A7,Data2!B4:R32,11,FALSE) -> 28.3 | G7: =(F7 - MIN($F$4:$F$8)) / (MAX($F$4:$F$8) - MIN($F$4:$F$8))*$F$3 -> 13.041492 | H7: =VLOOKUP(A7,Data2!B4:R32,3,FALSE) -> 51.91 | I7: =(MAX($H$4:$H$8) - H7) / (MAX($H$4:$H$8) - MIN($H$4:$H$8))*$H$3 -> 11.788166 | J7: =VLOOKUP(A7,Data2!B4:R32,12,FALSE) -> 0.02 | K7: =(MAX($J$4:$J$8) - J7) / (MAX($J$4:$J$8) - MIN($J$4:$J$8))*$J$3 -> 5 | L7: =VLOOKUP(A7,Data2!B4:R32,13,FALSE) -> 11.78 | M7: =(L7 - MIN($L$4:$L$8)) / (MAX($L$4:$L$8) - MIN($L$4:$L$8))*$L$3 -> 0 | N7: =VLOOKUP(A7,Data2!B4:S32,18,FALSE) -> -6.53 | O7: =(N7 - MIN($N$4:$N$8)) / (MAX($N$4:$N$8) - MIN($N$4:$N$8))*$N$3 -> 0 | P7: =VLOOKUP(A7,Data2!B4:R32,15,FALSE) -> 8.52 | Q7: =(P7 - MIN($P$4:$P$8)) / (MAX($P$4:$P$8) - MIN($P$4:$P$8))*$P$3 -> 0 | R7: =VLOOKUP(A7,Data2!B4:R32,16,FALSE) -> 7.26 | S7: =(R7 - MIN($R$4:$R$8)) / (MAX($R$4:$R$8) - MIN($R$4:$R$8))*$R$3 -> 1.6919941 | T7: =SUM(C7+E7+G7+I7+K7+M7+O7+Q7+S7) -> 31.521652 | U7: =RANK(T7,$T$4:$T$8,0) -> 5
A8: Blue Star | B8: =VLOOKUP(A8,Data2!B5:O32,14,FALSE) -> 20.62 | C8: =(B8 - MIN($B$4:$B$8)) / (MAX($B$4:$B$8) - MIN($B$4:$B$8))*$B$3 -> 13.33 | D8: =VLOOKUP(A8,Data2!B5:R33,10,FALSE) -> 26.2 | E8: =(D8 - MIN($D$4:$D$8)) / (MAX($D$4:$D$8) - MIN($D$4:$D$8))*$D$3 -> 13.33 | F8: =VLOOKUP(A8,Data2!B5:R33,11,FALSE) -> 28.75 | G8: =(F8 - MIN($F$4:$F$8)) / (MAX($F$4:$F$8) - MIN($F$4:$F$8))*$F$3 -> 13.34 | H8: =VLOOKUP(A8,Data2!B5:R33,3,FALSE) -> 61.47 | I8: =(MAX($H$4:$H$8) - H8) / (MAX($H$4:$H$8) - MIN($H$4:$H$8))*$H$3 -> 5.5377574 | J8: =VLOOKUP(A8,Data2!B5:R33,12,FALSE) -> 0.12 | K8: =(MAX($J$4:$J$8) - J8) / (MAX($J$4:$J$8) - MIN($J$4:$J$8))*$J$3 -> 0.83333333 | L8: =VLOOKUP(A8,Data2!B5:R33,13,FALSE) -> 16.92 | M8: =(L8 - MIN($L$4:$L$8)) / (MAX($L$4:$L$8) - MIN($L$4:$L$8))*$L$3 -> 0.78810181 | N8: =VLOOKUP(A8,Data2!B5:S33,18,FALSE) -> 52.42 | O8: =(N8 - MIN($N$4:$N$8)) / (MAX($N$4:$N$8) - MIN($N$4:$N$8))*$N$3 -> 10 | P8: =VLOOKUP(A8,Data2!B5:R33,15,FALSE) -> 25.43 | Q8: =(P8 - MIN($P$4:$P$8)) / (MAX($P$4:$P$8) - MIN($P$4:$P$8))*$P$3 -> 10 | R8: =VLOOKUP(A8,Data2!B5:R33,16,FALSE) -> 52.09 | S8: =(R8 - MIN($R$4:$R$8)) / (MAX($R$4:$R$8) - MIN($R$4:$R$8))*$R$3 -> 10 | T8: =SUM(C8+E8+G8+I8+K8+M8+O8+Q8+S8) -> 77.159193 | U8: =RANK(T8,$T$4:$T$8,0) -> 1
T9: =AVERAGE(T4:T8) -> 49.36783
H10: P/E Ratio | J10: Debt to Equity
H11: inverse metrics, lower the better | J11: inverse metrics, lower the better

Sheet Banking
A1: Stocks | B1: ROE ratio | C1: Weightage | D1: ROCE (%) | E1: Weightage | F1: EPS | G1: Weightage | H1: P/E Ratio | I1: Weightage | J1: Debt to Equity | K1: Weightage | L1: Interest Coverage Ratio | M1: Weightage | N1: Return over 3Y (%) | O1: Weightage | P1: Sales Growth 3Y (%) | Q1: Weightage | R1: Profit Growth 3Y (%) | S1: Weightage | T1: Total Score (Weighted) | U1: Final Rank
A2: Weightage | B2: 35 | H2: 20 | J2: 30 | N2: 15
A3: Metrics | B3: 11.67 | D3: 11.66 | F3: 11.67 | H3: 20 | J3: 15 | L3: 15 | N3: 5 | P3: 5 | R3: 5
A4: HDFC Bank | B4: =VLOOKUP(A4,Data2!B1:O28,14,FALSE) -> 14.45 | C4: =(B4 - MIN($B$4:$B$8)) / (MAX($B$4:$B$8) - MIN($B$4:$B$8))*$B$3 -> 2.3762443 | D4: =VLOOKUP(A4,Data2!B1:R29,10,FALSE) -> 7.51 | E4: =(D4 - MIN($D$4:$D$8)) / (MAX($D$4:$D$8) - MIN($D$4:$D$8))*$D$3 -> 6.1235971 | F4: =VLOOKUP(A4,Data2!B1:R29,11,FALSE) -> 92.26 | G4: =(F4 - MIN($F$4:$F$8)) / (MAX($F$4:$F$8) - MIN($F$4:$F$8))*$F$3 -> 9.5331762 | H4: =VLOOKUP(A4,Data2!B1:R29,3,FALSE) -> 22 | I4: =(MAX($H$4:$H$8) - H4) / (MAX($H$4:$H$8) - MIN($H$4:$H$8))*$H$3 -> 0 | J4: =VLOOKUP(A4,Data2!B1:R29,12,FALSE) -> 6.41 | K4: =(MAX($J$4:$J$8) - J4) / (MAX($J$4:$J$8) - MIN($J$4:$J$8))*$J$3 -> 4.1689373 | L4: =VLOOKUP(A4,Data2!B1:R29,13,FALSE) -> 1.5 | M4: =(L4 - MIN($L$4:$L$8)) / (MAX($L$4:$L$8) - MIN($L$4:$L$8))*$L$3 -> 0 | N4: =VLOOKUP(A4,Data2!B1:S29,18,FALSE) -> 12.98 | O4: =(N4 - MIN($N$4:$N$8)) / (MAX($N$4:$N$8) - MIN($N$4:$N$8))*$N$3 -> 1.0170488 | P4: =VLOOKUP(A4,Data2!B1:R29,15,FALSE) -> 35.26 | Q4: =(P4 - MIN($P$4:$P$8)) / (MAX($P$4:$P$8) - MIN($P$4:$P$8))*$P$3 -> 5 | R4: =VLOOKUP(A4,Data2!B1:R29,16,FALSE) -> 22.98 | S4: =(R4 - MIN($R$4:$R$8)) / (MAX($R$4:$R$8) - MIN($R$4:$R$8))*$R$3 -> 0.14925373 | T4: =SUM(C4+E4+G4+I4+K4+M4+O4+Q4+S4) -> 28.368257 | U4: =RANK(T4,$T$4:$T$8,0) -> 5
A5: ICICI Bank | B5: =VLOOKUP(A5,Data2!B2:O29,14,FALSE) -> 17.97 | C5: =(B5 - MIN($B$4:$B$8)) / (MAX($B$4:$B$8) - MIN($B$4:$B$8))*$B$3 -> 11.67 | D5: =VLOOKUP(A5,Data2!B2:R30,10,FALSE) -> 7.88 | E5: =(D5 - MIN($D$4:$D$8)) / (MAX($D$4:$D$8) - MIN($D$4:$D$8))*$D$3 -> 9.2273381 | F5: =VLOOKUP(A5,Data2!B2:R30,11,FALSE) -> 74.58 | G5: =(F5 - MIN($F$4:$F$8)) / (MAX($F$4:$F$8) - MIN($F$4:$F$8))*$F$3 -> 7.54794 | H5: =VLOOKUP(A5,Data2!B2:R30,3,FALSE) -> 20.09 | I5: =(MAX($H$4:$H$8) - H5) / (MAX($H$4:$H$8) - MIN($H$4:$H$8))*$H$3 -> 3.9381443 | J5: =VLOOKUP(A5,Data2!B2:R30,12,FALSE) -> 5.97 | K5: =(MAX($J$4:$J$8) - J5) / (MAX($J$4:$J$8) - MIN($J$4:$J$8))*$J$3 -> 5.9673025 | L5: =VLOOKUP(A5,Data2!B2:R30,13,FALSE) -> 1.83 | M5: =(L5 - MIN($L$4:$L$8)) / (MAX($L$4:$L$8) - MIN($L$4:$L$8))*$L$3 -> 9.5192308 | N5: =VLOOKUP(A5,Data2!B2:S30,18,FALSE) -> 22.81 | O5: =(N5 - MIN($N$4:$N$8)) / (MAX($N$4:$N$8) - MIN($N$4:$N$8))*$N$3 -> 2.4617872 | P5: =VLOOKUP(A5,Data2!B2:R30,15,FALSE) -> 25 | Q5: =(P5 - MIN($P$4:$P$8)) / (MAX($P$4:$P$8) - MIN($P$4:$P$8))*$P$3 -> 2.2741764 | R5: =VLOOKUP(A5,Data2!B2:R30,16,FALSE) -> 26.67 | S5: =(R5 - MIN($R$4:$R$8)) / (MAX($R$4:$R$8) - MIN($R$4:$R$8))*$R$3 -> 0.98371777 | T5: =SUM(C5+E5+G5+I5+K5+M5+O5+Q5+S5) -> 53.589637 | U5: =RANK(T5,$T$4:$T$8,0) -> 2
A6: IDBI Bank | B6: =VLOOKUP(A6,Data2!B3:O30,14,FALSE) -> 13.55 | C6: =(B6 - MIN($B$4:$B$8)) / (MAX($B$4:$B$8) - MIN($B$4:$B$8))*$B$3 -> 0 | D6: =VLOOKUP(A6,Data2!B3:R31,10,FALSE) -> 6.78 | E6: =(D6 - MIN($D$4:$D$8)) / (MAX($D$4:$D$8) - MIN($D$4:$D$8))*$D$3 -> 0 | F6: =VLOOKUP(A6,Data2!B3:R31,11,FALSE) -> 7.36 | G6: =(F6 - MIN($F$4:$F$8)) / (MAX($F$4:$F$8) - MIN($F$4:$F$8))*$F$3 -> 0 | H6: =VLOOKUP(A6,Data2!B3:R31,3,FALSE) -> 13.23 | I6: =(MAX($H$4:$H$8) - H6) / (MAX($H$4:$H$8) - MIN($H$4:$H$8))*$H$3 -> 18.082474 | J6: =VLOOKUP(A6,Data2!B3:R31,12,FALSE) -> 5.35 | K6: =(MAX($J$4:$J$8) - J6) / (MAX($J$4:$J$8) - MIN($J$4:$J$8))*$J$3 -> 8.5013624 | L6: =VLOOKUP(A6,Data2!B3:R31,13,FALSE) -> 1.73 | M6: =(L6 - MIN($L$4:$L$8)) / (MAX($L$4:$L$8) - MIN($L$4:$L$8))*$L$3 -> 6.6346154 | N6: =VLOOKUP(A6,Data2!B3:S31,18,FALSE) -> 40.08 | O6: =(N6 - MIN($N$4:$N$8)) / (MAX($N$4:$N$8) - MIN($N$4:$N$8))*$N$3 -> 5 | P6: =VLOOKUP(A6,Data2!B3:R31,15,FALSE) -> 16.44 | Q6: =(P6 - MIN($P$4:$P$8)) / (MAX($P$4:$P$8) - MIN($P$4:$P$8))*$P$3 -> 0 | R6: =VLOOKUP(A6,Data2!B3:R31,16,FALSE) -> 44.43 | S6: =(R6 - MIN($R$4:$R$8)) / (MAX($R$4:$R$8) - MIN($R$4:$R$8))*$R$3 -> 5 | T6: =SUM(C6+E6+G6+I6+K6+M6+O6+Q6+S6) -> 43.218452 | U6: =RANK(T6,$T$4:$T$8,0) -> 3
A7: Kotak Mah. Bank | B7: =VLOOKUP(A7,Data2!B4:O31,14,FALSE) -> 15.37 | C7: =(B7 - MIN($B$4:$B$8)) / (MAX($B$4:$B$8) - MIN($B$4:$B$8))*$B$3 -> 4.8052941 | D7: =VLOOKUP(A7,Data2!B4:R32,10,FALSE) -> 8.17 | E7: =(D7 - MIN($D$4:$D$8)) / (MAX($D$4:$D$8) - MIN($D$4:$D$8))*$D$3 -> 11.66 | F7: =VLOOKUP(A7,Data2!B4:R32,11,FALSE) -> 111.29 | G7: =(F7 - MIN($F$4:$F$8)) / (MAX($F$4:$F$8) - MIN($F$4:$F$8))*$F$3 -> 11.67 | H7: =VLOOKUP(A7,Data2!B4:R32,3,FALSE) -> 19.54 | I7: =(MAX($H$4:$H$8) - H7) / (MAX($H$4:$H$8) - MIN($H$4:$H$8))*$H$3 -> 5.0721649 | J7: =VLOOKUP(A7,Data2!B4:R32,12,FALSE) -> 3.76 | K7: =(MAX($J$4:$J$8) - J7) / (MAX($J$4:$J$8) - MIN($J$4:$J$8))*$J$3 -> 15 | L7: =VLOOKUP(A7,Data2!B4:R32,13,FALSE) -> 2.02 | M7: =(L7 - MIN($L$4:$L$8)) / (MAX($L$4:$L$8) - MIN($L$4:$L$8))*$L$3 -> 15 | N7: =VLOOKUP(A7,Data2!B4:S32,18,FALSE) -> 6.06 | O7: =(N7 - MIN($N$4:$N$8)) / (MAX($N$4:$N$8) - MIN($N$4:$N$8))*$N$3 -> 0 | P7: =VLOOKUP(A7,Data2!B4:R32,15,FALSE) -> 24.85 | Q7: =(P7 - MIN($P$4:$P$8)) / (MAX($P$4:$P$8) - MIN($P$4:$P$8))*$P$3 -> 2.2343252 | R7: =VLOOKUP(A7,Data2!B4:R32,16,FALSE) -> 22.32 | S7: =(R7 - MIN($R$4:$R$8)) / (MAX($R$4:$R$8) - MIN($R$4:$R$8))*$R$3 -> 0 | T7: =SUM(C7+E7+G7+I7+K7+M7+O7+Q7+S7) -> 65.441784 | U7: =RANK(T7,$T$4:$T$8,0) -> 1
A8: Axis Bank | B8: =VLOOKUP(A8,Data2!B5:O32,14,FALSE) -> 16.3 | C8: =(B8 - MIN($B$4:$B$8)) / (MAX($B$4:$B$8) - MIN($B$4:$B$8))*$B$3 -> 7.2607466 | D8: =VLOOKUP(A8,Data2!B5:R33,10,FALSE) -> 7.11 | E8: =(D8 - MIN($D$4:$D$8)) / (MAX($D$4:$D$8) - MIN($D$4:$D$8))*$D$3 -> 2.7682014 | F8: =VLOOKUP(A8,Data2!B5:R33,11,FALSE) -> 89.98 | G8: =(F8 - MIN($F$4:$F$8)) / (MAX($F$4:$F$8) - MIN($F$4:$F$8))*$F$3 -> 9.2771616 | H8: =VLOOKUP(A8,Data2!B5:R33,3,FALSE) -> 12.3 | I8: =(MAX($H$4:$H$8) - H8) / (MAX($H$4:$H$8) - MIN($H$4:$H$8))*$H$3 -> 20 | J8: =VLOOKUP(A8,Data2!B5:R33,12,FALSE) -> 7.43 | K8: =(MAX($J$4:$J$8) - J8) / (MAX($J$4:$J$8) - MIN($J$4:$J$8))*$J$3 -> 0 | L8: =VLOOKUP(A8,Data2!B5:R33,13,FALSE) -> 1.5 | M8: =(L8 - MIN($L$4:$L$8)) / (MAX($L$4:$L$8) - MIN($L$4:$L$8))*$L$3 -> 0 | N8: =VLOOKUP(A8,Data2!B5:S33,18,FALSE) -> 14.61 | O8: =(N8 - MIN($N$4:$N$8)) / (MAX($N$4:$N$8) - MIN($N$4:$N$8))*$N$3 -> 1.2566138 | P8: =VLOOKUP(A8,Data2!B5:R33,15,FALSE) -> 22.76 | Q8: =(P8 - MIN($P$4:$P$8)) / (MAX($P$4:$P$8) - MIN($P$4:$P$8))*$P$3 -> 1.6790648 | R8: =VLOOKUP(A8,Data2!B5:R33,16,FALSE) -> 25.72 | S8: =(R8 - MIN($R$4:$R$8)) / (MAX($R$4:$R$8) - MIN($R$4:$R$8))*$R$3 -> 0.76888286 | T8: =SUM(C8+E8+G8+I8+K8+M8+O8+Q8+S8) -> 43.010671 | U8: =RANK(T8,$T$4:$T$8,0) -> 4
T9: =AVERAGE(T4:T8) -> 46.72576
H11: P/E Ratio | J11: Debt to Equity
H12: inverse metrics, lower the better | J12: inverse metrics, lower the better

Sheet Auto. M
A1: Stocks | B1: ROE ratio | C1: Weightage | D1: ROCE (%) | E1: Weightage | F1: EPS | G1: Weightage | H1: P/E Ratio | I1: Weightage | J1: Debt to Equity | K1: Weightage | L1: Interest Coverage Ratio | M1: Weightage | N1: Return over 3Y (%) | O1: Weightage | P1: Sales Growth 3Y (%) | Q1: Weightage | R1: Profit Growth 3Y (%) | S1: Weightage | T1: Total Score (Weighted) | U1: Final Rank
A2: Weightage | B2: 35 | H2: 20 | J2: 15 | N2: 30
A3: Metrics | B3: 11.67 | D3: 11.67 | F3: 11.66 | H3: 20 | J3: 7.5 | L3: 7.5 | N3: 10 | P3: 10 | R3: 10
A4: Maruti Suzuki | B4: =VLOOKUP(A4,Data2!B1:O28,14,FALSE) -> 15.95 | C4: =(B4 - MIN($B$4:$B$8)) / (MAX($B$4:$B$8) - MIN($B$4:$B$8))*$B$3 -> 0 | D4: =VLOOKUP(A4,Data2!B1:R29,10,FALSE) -> 21.76 | E4: =(D4 - MIN($D$4:$D$8)) / (MAX($D$4:$D$8) - MIN($D$4:$D$8))*$D$3 -> 5.7577883 | F4: =VLOOKUP(A4,Data2!B1:R29,11,FALSE) -> 461.2 | G4: =(F4 - MIN($F$4:$F$8)) / (MAX($F$4:$F$8) - MIN($F$4:$F$8))*$F$3 -> 7.7769637 | H4: =VLOOKUP(A4,Data2!B1:R29,3,FALSE) -> 27.37 | I4: =(MAX($H$4:$H$8) - H4) / (MAX($H$4:$H$8) - MIN($H$4:$H$8))*$H$3 -> 7.045134 | J4: =VLOOKUP(A4,Data2!B1:R29,12,FALSE) -> 0 | K4: =(MAX($J$4:$J$8) - J4) / (MAX($J$4:$J$8) - MIN($J$4:$J$8))*$J$3 -> 7.5 | L4: =VLOOKUP(A4,Data2!B1:R29,13,FALSE) -> 102.03 | M4: =(L4 - MIN($L$4:$L$8)) / (MAX($L$4:$L$8) - MIN($L$4:$L$8))*$L$3 -> 7.5 | N4: =VLOOKUP(A4,Data2!B1:S29,18,FALSE) -> 13.35 | O4: =(N4 - MIN($N$4:$N$8)) / (MAX($N$4:$N$8) - MIN($N$4:$N$8))*$N$3 -> 0.19489863 | P4: =VLOOKUP(A4,Data2!B1:R29,15,FALSE) -> 20.07 | Q4: =(P4 - MIN($P$4:$P$8)) / (MAX($P$4:$P$8) - MIN($P$4:$P$8))*$P$3 -> 2.3011928 | R4: =VLOOKUP(A4,Data2!B1:R29,16,FALSE) -> 72.51 | S4: =(R4 - MIN($R$4:$R$8)) / (MAX($R$4:$R$8) - MIN($R$4:$R$8))*$R$3 -> 6.9566678 | T4: =SUM(C4+E4+G4+I4+K4+M4+O4+Q4+S4) -> 45.032645 | U4: =RANK(T4,$T$4:$T$8,0) -> 4
A5: Tata Motors | B5: =VLOOKUP(A5,Data2!B2:O29,14,FALSE) -> 28.08 | C5: =(B5 - MIN($B$4:$B$8)) / (MAX($B$4:$B$8) - MIN($B$4:$B$8))*$B$3 -> 11.67 | D5: =VLOOKUP(A5,Data2!B2:R30,10,FALSE) -> 19.97 | E5: =(D5 - MIN($D$4:$D$8)) / (MAX($D$4:$D$8) - MIN($D$4:$D$8))*$D$3 -> 4.4415123 | F5: =VLOOKUP(A5,Data2!B2:R30,11,FALSE) -> 75.6 | G5: =(F5 - MIN($F$4:$F$8)) / (MAX($F$4:$F$8) - MIN($F$4:$F$8))*$F$3 -> 0 | H5: =VLOOKUP(A5,Data2!B2:R30,3,FALSE) -> 9 | I5: =(MAX($H$4:$H$8) - H5) / (MAX($H$4:$H$8) - MIN($H$4:$H$8))*$H$3 -> 20 | J5: =VLOOKUP(A5,Data2!B2:R30,12,FALSE) -> 0.62 | K5: =(MAX($J$4:$J$8) - J5) / (MAX($J$4:$J$8) - MIN($J$4:$J$8))*$J$3 -> 4.7155689 | L5: =VLOOKUP(A5,Data2!B2:R30,13,FALSE) -> 7.75 | M5: =(L5 - MIN($L$4:$L$8)) / (MAX($L$4:$L$8) - MIN($L$4:$L$8))*$L$3 -> 0.35252199 | N5: =VLOOKUP(A5,Data2!B2:S30,18,FALSE) -> 15.93 | O5: =(N5 - MIN($N$4:$N$8)) / (MAX($N$4:$N$8) - MIN($N$4:$N$8))*$N$3 -> 0.36363636 | P5: =VLOOKUP(A5,Data2!B2:R30,15,FALSE) -> 16.45 | Q5: =(P5 - MIN($P$4:$P$8)) / (MAX($P$4:$P$8) - MIN($P$4:$P$8))*$P$3 -> 0.50198807 | R5: =VLOOKUP(A5,Data2!B2:R30,16,FALSE) -> 65.49 | S5: =(R5 - MIN($R$4:$R$8)) / (MAX($R$4:$R$8) - MIN($R$4:$R$8))*$R$3 -> 6.1706416 | T5: =SUM(C5+E5+G5+I5+K5+M5+O5+Q5+S5) -> 48.215869 | U5: =RANK(T5,$T$4:$T$8,0) -> 3
A6: M & M | B6: =VLOOKUP(A6,Data2!B3:O30,14,FALSE) -> 18.05 | C6: =(B6 - MIN($B$4:$B$8)) / (MAX($B$4:$B$8) - MIN($B$4:$B$8))*$B$3 -> 2.0203627 | D6: =VLOOKUP(A6,Data2!B3:R31,10,FALSE) -> 13.93 | E6: =(D6 - MIN($D$4:$D$8)) / (MAX($D$4:$D$8) - MIN($D$4:$D$8))*$D$3 -> 0 | F6: =VLOOKUP(A6,Data2!B3:R31,11,FALSE) -> 103.97 | G6: =(F6 - MIN($F$4:$F$8)) / (MAX($F$4:$F$8) - MIN($F$4:$F$8))*$F$3 -> 0.57217961 | H6: =VLOOKUP(A6,Data2!B3:R31,3,FALSE) -> 31.42 | I6: =(MAX($H$4:$H$8) - H6) / (MAX($H$4:$H$8) - MIN($H$4:$H$8))*$H$3 -> 4.1889986 | J6: =VLOOKUP(A6,Data2!B3:R31,12,FALSE) -> 1.67 | K6: =(MAX($J$4:$J$8) - J6) / (MAX($J$4:$J$8) - MIN($J$4:$J$8))*$J$3 -> 0 | L6: =VLOOKUP(A6,Data2!B3:R31,13,FALSE) -> 3.1 | M6: =(L6 - MIN($L$4:$L$8)) / (MAX($L$4:$L$8) - MIN($L$4:$L$8))*$L$3 -> 0 | N6: =VLOOKUP(A6,Data2!B3:S31,18,FALSE) -> 10.37 | O6: =(N6 - MIN($N$4:$N$8)) / (MAX($N$4:$N$8) - MIN($N$4:$N$8))*$N$3 -> 0 | P6: =VLOOKUP(A6,Data2!B3:R31,15,FALSE) -> 20.87 | Q6: =(P6 - MIN($P$4:$P$8)) / (MAX($P$4:$P$8) - MIN($P$4:$P$8))*$P$3 -> 2.6988072 | R6: =VLOOKUP(A6,Data2!B3:R31,16,FALSE) -> 27.17 | S6: =(R6 - MIN($R$4:$R$8)) / (MAX($R$4:$R$8) - MIN($R$4:$R$8))*$R$3 -> 1.8799686 | T6: =SUM(C6+E6+G6+I6+K6+M6+O6+Q6+S6) -> 11.360317 | U6: =RANK(T6,$T$4:$T$8,0) -> 5
A7: Force Motors | B7: =VLOOKUP(A7,Data2!B4:O31,14,FALSE) -> 20.68 | C7: =(B7 - MIN($B$4:$B$8)) / (MAX($B$4:$B$8) - MIN($B$4:$B$8))*$B$3 -> 4.5506265 | D7: =VLOOKUP(A7,Data2!B4:R32,10,FALSE) -> 29.8 | E7: =(D7 - MIN($D$4:$D$8)) / (MAX($D$4:$D$8) - MIN($D$4:$D$8))*$D$3 -> 11.67 | F7: =VLOOKUP(A7,Data2!B4:R32,11,FALSE) -> 653.73 | G7: =(F7 - MIN($F$4:$F$8)) / (MAX($F$4:$F$8) - MIN($F$4:$F$8))*$F$3 -> 11.66 | H7: =VLOOKUP(A7,Data2!B4:R32,3,FALSE) -> 37.36 | I7: =(MAX($H$4:$H$8) - H7) / (MAX($H$4:$H$8) - MIN($H$4:$H$8))*$H$3 -> 0 | J7: =VLOOKUP(A7,Data2!B4:R32,12,FALSE) -> 0.01 | K7: =(MAX($J$4:$J$8) - J7) / (MAX($J$4:$J$8) - MIN($J$4:$J$8))*$J$3 -> 7.4550898 | L7: =VLOOKUP(A7,Data2!B4:R32,13,FALSE) -> 56.47 | M7: =(L7 - MIN($L$4:$L$8)) / (MAX($L$4:$L$8) - MIN($L$4:$L$8))*$L$3 -> 4.0460427 | N7: =VLOOKUP(A7,Data2!B4:S32,18,FALSE) -> 163.27 | O7: =(N7 - MIN($N$4:$N$8)) / (MAX($N$4:$N$8) - MIN($N$4:$N$8))*$N$3 -> 10 | P7: =VLOOKUP(A7,Data2!B4:R32,15,FALSE) -> 35.56 | Q7: =(P7 - MIN($P$4:$P$8)) / (MAX($P$4:$P$8) - MIN($P$4:$P$8))*$P$3 -> 10 | R7: =VLOOKUP(A7,Data2!B4:R32,16,FALSE) -> 99.69 | S7: =(R7 - MIN($R$4:$R$8)) / (MAX($R$4:$R$8) - MIN($R$4:$R$8))*$R$3 -> 10 | T7: =SUM(C7+E7+G7+I7+K7+M7+O7+Q7+S7) -> 69.381759 | U7: =RANK(T7,$T$4:$T$8,0) -> 1
A8: Bajaj Auto | B8: =VLOOKUP(A8,Data2!B5:O32,14,FALSE) -> 22.77 | C8: =(B8 - MIN($B$4:$B$8)) / (MAX($B$4:$B$8) - MIN($B$4:$B$8))*$B$3 -> 6.5613685 | D8: =VLOOKUP(A8,Data2!B5:R33,10,FALSE) -> 28.06 | E8: =(D8 - MIN($D$4:$D$8)) / (MAX($D$4:$D$8) - MIN($D$4:$D$8))*$D$3 -> 10.390491 | F8: =VLOOKUP(A8,Data2!B5:R33,11,FALSE) -> 262.29 | G8: =(F8 - MIN($F$4:$F$8)) / (MAX($F$4:$F$8) - MIN($F$4:$F$8))*$F$3 -> 3.7652525 | H8: =VLOOKUP(A8,Data2!B5:R33,3,FALSE) -> 9.45 | I8: =(MAX($H$4:$H$8) - H8) / (MAX($H$4:$H$8) - MIN($H$4:$H$8))*$H$3 -> 19.682652 | J8: =VLOOKUP(A8,Data2!B5:R33,12,FALSE) -> 0.27 | K8: =(MAX($J$4:$J$8) - J8) / (MAX($J$4:$J$8) - MIN($J$4:$J$8))*$J$3 -> 6.2874251 | L8: =VLOOKUP(A8,Data2!B5:R33,13,FALSE) -> 27.21 | M8: =(L8 - MIN($L$4:$L$8)) / (MAX($L$4:$L$8) - MIN($L$4:$L$8))*$L$3 -> 1.8278075 | N8: =VLOOKUP(A8,Data2!B5:S33,18,FALSE) -> 27.26 | O8: =(N8 - MIN($N$4:$N$8)) / (MAX($N$4:$N$8) - MIN($N$4:$N$8))*$N$3 -> 1.1046436 | P8: =VLOOKUP(A8,Data2!B5:R33,15,FALSE) -> 15.44 | Q8: =(P8 - MIN($P$4:$P$8)) / (MAX($P$4:$P$8) - MIN($P$4:$P$8))*$P$3 -> 0 | R8: =VLOOKUP(A8,Data2!B5:R33,16,FALSE) -> 10.38 | S8: =(R8 - MIN($R$4:$R$8)) / (MAX($R$4:$R$8) - MIN($R$4:$R$8))*$R$3 -> 0 | T8: =SUM(C8+E8+G8+I8+K8+M8+O8+Q8+S8) -> 49.61964 | U8: =RANK(T8,$T$4:$T$8,0) -> 2
T9: =AVERAGE(T4:T8) -> 44.722046
H11: P/E Ratio | J11: Debt to Equity
H12: inverse metrics, lower the better | J12: inverse metrics, lower the better

Sheet data
A1: Stocks | B1: ROE ratio | C1: ROCE (%) | D1: EPS | E1: Return over 3Y (%) | F1: YOY Profit Growth (%) | G1: P/E Ratio | H1: P/B Ratio | I1: Debt to Equity | J1: Interest Coverage Ratio | K1: Sales Growth 3Y (%) | L1: Profit Growth 3Y (%) | M1: YOY Sales Growth (%) | N1: Total Score (Weighted) | O1: Final Rank
A2: Weightage
A3: HDFC Bank | B3: =VLOOKUP(A3,Data2!B1:O28,14,FALSE) -> 14.45 | C3: =VLOOKUP(A3,Data2!B1:R29,10,FALSE) -> 7.51 | D3: =VLOOKUP(A3,Data2!B1:R29,11,FALSE) -> 92.26 | E3: =VLOOKUP(A3,Data2!B1:S29,18,FALSE) -> 12.98 | F3: 10.5 | G3: =VLOOKUP(A3,Data2!B1:R29,3,FALSE) -> 22 | I3: =VLOOKUP(A3,Data2!B1:R29,12,FALSE) -> 6.41 | J3: =VLOOKUP(A3,Data2!B1:R29,13,FALSE) -> 1.5 | K3: =VLOOKUP(A3,Data2!B1:R29,15,FALSE) -> 35.26 | L3: =VLOOKUP(A3,Data2!B1:R29,16,FALSE) -> 22.98 | M3: 18.58
A4: ICICI Bank | B4: =VLOOKUP(A4,Data2!B2:O29,14,FALSE) -> 17.97 | C4: =VLOOKUP(A4,Data2!B2:R30,10,FALSE) -> 7.88 | D4: =VLOOKUP(A4,Data2!B2:R30,11,FALSE) -> 74.58 | E4: =VLOOKUP(A4,Data2!B2:S30,18,FALSE) -> 22.81 | F4: 15.3 | G4: =VLOOKUP(A4,Data2!B2:R30,3,FALSE) -> 20.09 | I4: =VLOOKUP(A4,Data2!B2:R30,12,FALSE) -> 5.97 | J4: =VLOOKUP(A4,Data2!B2:R30,13,FALSE) -> 1.83 | K4: =VLOOKUP(A4,Data2!B2:R30,15,FALSE) -> 25 | L4: =VLOOKUP(A4,Data2!B2:R30,16,FALSE) -> 26.67 | M4: 16.81
A5: IDBI Bank | B5: =VLOOKUP(A5,Data2!B3:O30,14,FALSE) -> 13.55 | C5: =VLOOKUP(A5,Data2!B3:R31,10,FALSE) -> 6.78 | D5: =VLOOKUP(A5,Data2!B3:R31,11,FALSE) -> 7.36 | E5: =VLOOKUP(A5,Data2!B3:S31,18,FALSE) -> 40.08 | F5: 3.73 | G5: =VLOOKUP(A5,Data2!B3:R31,3,FALSE) -> 13.23 | I5: =VLOOKUP(A5,Data2!B3:R31,12,FALSE) -> 5.35 | J5: =VLOOKUP(A5,Data2!B3:R31,13,FALSE) -> 1.73 | K5: =VLOOKUP(A5,Data2!B3:R31,15,FALSE) -> 16.44 | L5: =VLOOKUP(A5,Data2!B3:R31,16,FALSE) -> 44.43 | M5: 9.34
A6: Kotak Mah. Bank | B6: =VLOOKUP(A6,Data2!B4:O31,14,FALSE) -> 15.37 | C6: =VLOOKUP(A6,Data2!B4:R32,10,FALSE) -> 8.17 | D6: =VLOOKUP(A6,Data2!B4:R32,11,FALSE) -> 111.29 | E6: =VLOOKUP(A6,Data2!B4:S32,18,FALSE) -> 6.06 | F6: 21.48 | G6: =VLOOKUP(A6,Data2!B4:R32,3,FALSE) -> 19.54 | I6: =VLOOKUP(A6,Data2!B4:R32,12,FALSE) -> 3.76 | J6: =VLOOKUP(A6,Data2!B4:R32,13,FALSE) -> 2.02 | K6: =VLOOKUP(A6,Data2!B4:R32,15,FALSE) -> 24.85 | L6: =VLOOKUP(A6,Data2!B4:R32,16,FALSE) -> 22.32 | M6: 16.77
A7: Axis Bank | B7: =VLOOKUP(A7,Data2!B5:O32,14,FALSE) -> 16.3 | C7: =VLOOKUP(A7,Data2!B5:R33,10,FALSE) -> 7.11 | D7: =VLOOKUP(A7,Data2!B5:R33,11,FALSE) -> 89.98 | E7: =VLOOKUP(A7,Data2!B5:S33,18,FALSE) -> 14.61 | F7: 6.32 | G7: =VLOOKUP(A7,Data2!B5:R33,3,FALSE) -> 12.3 | I7: =VLOOKUP(A7,Data2!B5:R33,12,FALSE) -> 7.43 | J7: =VLOOKUP(A7,Data2!B5:R33,13,FALSE) -> 1.5 | K7: =VLOOKUP(A7,Data2!B5:R33,15,FALSE) -> 22.76 | L7: =VLOOKUP(A7,Data2!B5:R33,16,FALSE) -> 25.72 | M7: 12.96
A8: Voltas | B8: =VLOOKUP(A8,Data2!B6:O33,14,FALSE) -> 13.35 | C8: =VLOOKUP(A8,Data2!B6:R34,10,FALSE) -> 17.64 | D8: =VLOOKUP(A8,Data2!B6:R34,11,FALSE) -> 25.43 | E8: =VLOOKUP(A8,Data2!B6:S34,18,FALSE) -> 10.37 | F8: 233.87 | G8: =VLOOKUP(A8,Data2!B6:R34,3,FALSE) -> 54.95 | I8: =VLOOKUP(A8,Data2!B6:R34,12,FALSE) -> 0.14 | J8: =VLOOKUP(A8,Data2!B6:R34,13,FALSE) -> 19.92 | K8: =VLOOKUP(A8,Data2!B6:R34,15,FALSE) -> 24.77 | L8: =VLOOKUP(A8,Data2!B6:R34,16,FALSE) -> 17.71 | M8: 23.48
A9: Havells India | B9: =VLOOKUP(A9,Data2!B7:O34,14,FALSE) -> 18.79 | C9: =VLOOKUP(A9,Data2!B7:R35,10,FALSE) -> 25.32 | D9: =VLOOKUP(A9,Data2!B7:R35,11,FALSE) -> 22.52 | E9: =VLOOKUP(A9,Data2!B7:S35,18,FALSE) -> 8.17 | F9: 15.85 | G9: =VLOOKUP(A9,Data2!B7:R35,3,FALSE) -> 69.94 | I9: =VLOOKUP(A9,Data2!B7:R35,12,FALSE) -> 0.04 | J9: =VLOOKUP(A9,Data2!B7:R35,13,FALSE) -> 44.39 | K9: =VLOOKUP(A9,Data2!B7:R35,15,FALSE) -> 16.04 | L9: =VLOOKUP(A9,Data2!B7:R35,16,FALSE) -> 7.37 | M9: 17.14
A10: Crompton Gr. Con | B10: =VLOOKUP(A10,Data2!B8:O35,14,FALSE) -> 17.4 | C10: =VLOOKUP(A10,Data2!B8:R36,10,FALSE) -> 19.01 | D10: =VLOOKUP(A10,Data2!B8:R36,11,FALSE) -> 8.64 | E10: =VLOOKUP(A10,Data2!B8:S36,18,FALSE) -> -3.78 | F10: 26.37 | G10: =VLOOKUP(A10,Data2!B8:R36,3,FALSE) -> 39.35 | I10: =VLOOKUP(A10,Data2!B8:R36,12,FALSE) -> 0.14 | J10: =VLOOKUP(A10,Data2!B8:R36,13,FALSE) -> 16.76 | K10: =VLOOKUP(A10,Data2!B8:R36,15,FALSE) -> 13.39 | L10: =VLOOKUP(A10,Data2!B8:R36,16,FALSE) -> -1.87 | M10: 7.53
A11: Whirlpool India | B11: =VLOOKUP(A11,Data2!B9:O36,14,FALSE) -> 9.27 | C11: =VLOOKUP(A11,Data2!B9:R37,10,FALSE) -> 12.99 | D11: =VLOOKUP(A11,Data2!B9:R37,11,FALSE) -> 28.3 | E11: =VLOOKUP(A11,Data2!B9:S37,18,FALSE) -> -6.53 | F11: 65.4 | G11: =VLOOKUP(A11,Data2!B9:R37,3,FALSE) -> 51.91 | I11: =VLOOKUP(A11,Data2!B9:R37,12,FALSE) -> 0.02 | J11: =VLOOKUP(A11,Data2!B9:R37,13,FALSE) -> 11.78 | K11: =VLOOKUP(A11,Data2!B9:R37,15,FALSE) -> 8.52 | L11: =VLOOKUP(A11,Data2!B9:R37,16,FALSE) -> 7.26 | M11: 15.95
A12: Blue Star | B12: =VLOOKUP(A12,Data2!B10:O37,14,FALSE) -> 20.62 | C12: =VLOOKUP(A12,Data2!B10:R38,10,FALSE) -> 26.2 | D12: =VLOOKUP(A12,Data2!B10:R38,11,FALSE) -> 28.75 | E12: =VLOOKUP(A12,Data2!B10:S38,18,FALSE) -> 52.42 | F12: 42.48 | G12: =VLOOKUP(A12,Data2!B10:R38,3,FALSE) -> 61.47 | I12: =VLOOKUP(A12,Data2!B10:R38,12,FALSE) -> 0.12 | J12: =VLOOKUP(A12,Data2!B10:R38,13,FALSE) -> 16.92 | K12: =VLOOKUP(A12,Data2!B10:R38,15,FALSE) -> 25.43 | L12: =VLOOKUP(A12,Data2!B10:R38,16,FALSE) -> 52.09 | M12: 23.56
A13: Maruti Suzuki | B13: =VLOOKUP(A13,Data2!B11:O38,14,FALSE) -> 15.95 | C13: =VLOOKUP(A13,Data2!B11:R39,10,FALSE) -> 21.76 | D13: =VLOOKUP(A13,Data2!B11:R39,11,FALSE) -> 461.2 | E13: =VLOOKUP(A13,Data2!B11:S39,18,FALSE) -> 13.35 | F13: 7.5 | G13: =VLOOKUP(A13,Data2!B11:R39,3,FALSE) -> 27.37 | I13: =VLOOKUP(A13,Data2!B11:R39,12,FALSE) -> 0 | J13: =VLOOKUP(A13,Data2!B11:R39,13,FALSE) -> 102.03 | K13: =VLOOKUP(A13,Data2!B11:R39,15,FALSE) -> 20.07 | L13: =VLOOKUP(A13,Data2!B11:R39,16,FALSE) -> 72.51 | M13: 7.79
A14: Tata Motors | B14: =VLOOKUP(A14,Data2!B12:O39,14,FALSE) -> 28.08 | C14: =VLOOKUP(A14,Data2!B12:R40,10,FALSE) -> 19.97 | D14: =VLOOKUP(A14,Data2!B12:R40,11,FALSE) -> 75.6 | E14: =VLOOKUP(A14,Data2!B12:S40,18,FALSE) -> 15.93 | F14: -11.36 | G14: =VLOOKUP(A14,Data2!B12:R40,3,FALSE) -> 9 | I14: =VLOOKUP(A14,Data2!B12:R40,12,FALSE) -> 0.62 | J14: =VLOOKUP(A14,Data2!B12:R40,13,FALSE) -> 7.75 | K14: =VLOOKUP(A14,Data2!B12:R40,15,FALSE) -> 16.45 | L14: =VLOOKUP(A14,Data2!B12:R40,16,FALSE) -> 65.49 | M14: 1.3
... A17: Bajaj Auto | B17: =VLOOKUP(A17,Data2!B15:O42,14,FALSE) -> 22.77 | C17: =VLOOKUP(A17,Data2!B15:R43,10,FALSE) -> 28.06 | D17: =VLOOKUP(A17,Data2!B15:R43,11,FALSE) -> 262.29 | E17: =VLOOKUP(A17,Data2!B15:S43,18,FALSE) -> 27.26 | F17: -4.97 | G17: =VLOOKUP(A17,Data2!B15:R43,3,FALSE) -> 9.45 | I17: =VLOOKUP(A17,Data2!B15:R43,12,FALSE) -> 0.27 | J17: =VLOOKUP(A17,Data2!B15:R43,13,FALSE) -> 27.21 | K17: =VLOOKUP(A17,Data2!B15:R43,15,FALSE) -> 15.44 | L17: =VLOOKUP(A17,Data2!B15:R43,16,FALSE) -> 10.38 | M17: 13.64

Sheet Data2
A1: S.No. | B1: Name | C1: CMP Rs. | D1: P/E | E1: Mar Cap Rs.Cr. | F1: Div Yld % | G1: NP Qtr Rs.Cr. | H1: Qtr Profit Var % | I1: Sales Qtr Rs.Cr. | J1: Qtr Sales Var % | K1: ROCE % | L1: EPS 12M Rs. | M1: Debt / Eq | N1: Int Coverage | O1: ROE % | P1: Sales Var 3Yrs % | Q1: Profit Var 3Yrs % | R1: CMP / BV | S1: 3Yrs return %
A2: 1 | B2: HDFC Bank | C2: 2024.3 | D2: 22 | E2: 1552486.5 | F2: 1.09 | G2: 17090.43 | H2: -1.32 | I2: 87371.87 | J2: 7.14 | K2: 7.51 | L2: 92.26 | M2: 6.41 | N2: 1.5 | O2: 14.45 | P2: 35.26 | Q2: 22.98 | R2: 2.97 | S2: 12.98
A3: 2 | B3: ICICI Bank | C3: 1488.6 | D3: 20.09 | E3: 1062372.4 | F3: 0.74 | G3: 14456.33 | H3: 15.92 | I3: 49079.96 | J3: 10.09 | K3: 7.88 | L3: 74.58 | M3: 5.97 | N3: 1.83 | O3: 17.97 | P3: 25 | Q3: 26.67 | R3: 3.4 | S3: 22.81
A4: 3 | B4: Kotak Mah. Bank | C4: 2170.4 | D4: 19.54 | E4: 431610.1 | F4: 0.12 | G4: 4932.76 | H4: -7.58 | I4: 16771.93 | J4: 10.66 | K4: 8.17 | L4: 111.29 | M4: 3.76 | N4: 2.02 | O4: 15.37 | P4: 24.85 | Q4: 22.32 | R4: 2.74 | S4: 6.06
A5: 4 | B5: Axis Bank | C5: 1104.8 | D5: 12.3 | E5: 342634.75 | F5: 0.09 | G5: 6279.49 | H5: -2.99 | I5: 32348.31 | J5: 3.82 | K5: 7.11 | L5: 89.98 | M5: 7.43 | N5: 1.5 | O5: 16.3 | P5: 22.76 | Q5: 25.72 | R5: 1.83 | S5: 14.61
A6: 5 | B6: IDBI Bank | C6: 97.38 | D6: 13.23 | E6: 104717.88 | F6: 2.16 | G6: 2023.87 | H6: 16.42 | I6: 7026.62 | J6: 5.35 | K6: 6.78 | L6: 7.36 | M6: 5.35 | N6: 1.73 | O6: 13.55 | P6: 16.44 | Q6: 44.43 | R6: 1.7 | S6: 40.08
A7: 6 | B7: IndusInd Bank | C7: 851.15 | D7: 25.1 | E7: 66336.87 | F7: 1.94 | G7: -2235.99 | H7: -195.28 | I7: 10633.85 | J7: -12.83 | K7: 6.49 | L7: 33.92 | M7: 7.22 | N7: 1.12 | O7: 4.16 | P7: 16.45 | Q7: -16.94 | R7: 1.03 | S7: -4.12
A8: 7 | B8: Yes Bank | C8: 19.9 | D8: 22.77 | E8: 62358.45 | F8: 0 | G8: 808.65 | H8: 56.72 | I8: 7604.62 | J8: -1.56 | K8: 6.36 | L8: 0.87 | M8: 7.45 | N8: 1.17 | O8: 5.44 | P8: 17.58 | Q8: 31.6 | R8: 1.3 | S8: 11.98
A9: 8 | B9: Titan Company | C9: 3471.4 | D9: 92.43 | E9: 308359.26 | F9: 0.32 | G9: 871 | H9: 12.97 | I9: 14916 | J9: 19.39 | K9: 19.14 | L9: 37.59 | M9: 1.79 | N9: 5.76 | O9: 31.75 | P9: 28.04 | Q9: 14.64 | R9: 26.51 | S9: 14.37
A10: 9 | B10: Asian Paints | C10: 2375.4 | D10: 58.05 | E10: 227852.66 | F10: 1.04 | G10: 700.83 | H10: -35.15 | I10: 8358.91 | J10: -4.26 | K10: 25.72 | L10: 38.23 | M10: 0.12 | N10: 25.06 | O10: 20.59 | P10: 5.23 | Q10: 8.4 | R10: 11.74 | S10: -8.84
A11: 10 | B11: Dixon Technolog. | C11: 16556 | D11: 116.73 | E11: 100165.73 | F11: 0.03 | G11: 280.02 | H11: 68.29 | I11: 12835.66 | J11: 95.08 | K11: 39.81 | L11: 197.39 | M11: 0.22 | N11: 9.22 | O11: 32.92 | P11: 53.73 | Q11: 59.81 | R11: 33.13 | S11: 64.54
A12: 11 | B12: Havells India | C12: 1572.7 | D12: 69.94 | E12: 98636.61 | F12: 0.64 | G12: 347.53 | H12: -14.72 | I12: 5455.35 | J12: -6.04 | K12: 25.32 | L12: 22.52 | M12: 0.04 | N12: 44.39 | O12: 18.79 | P12: 16.04 | Q12: 7.37 | R12: 11.85 | S12: 8.17
A13: 12 | B13: Berger Paints | C13: 576.2 | D13: 57.52 | E13: 67208.31 | F13: 0.66 | G13: 262.91 | H13: 17.99 | I13: 2704.03 | J13: 7.29 | K13: 24.9 | L13: 10.12 | M13: 0.11 | N13: 25.54 | O13: 20.26 | P13: 9.63 | Q13: 12.41 | R13: 10.92 | S13: 5.21
... A24: 23 | B24: Tata Motors | C24: 690.1 | D24: 9 | E24: 254112.56 | F24: 0.87 | G24: 8556 | H24: -49.58 | I24: 119503 | J24: 0.39 | K24: 19.97 | L24: 75.6 | M24: 0.62 | N24: 7.75 | O24: 28.08 | P24: 16.45 | Q24: 65.49 | R24: 2.19 | S24: 15.93
A25: 24 | B25: Hyundai Motor I | C25: 2117.1 | D25: 31.34 | E25: 172104.46 | F25: 0 | G25: 1582.56 | H25: -4.05 | I25: 17561.95 | J25: 2.51 | K25: 54.22 | L25: 67.59 | M25: 0.05 | N25: 59.13 | O25: 42.16 | P25: 12.88 | Q25: 24.22 | R25: 10.91
A26: 25 | B26: Force Motors | C26: 17140 | D26: 37.36 | E26: 22584.11 | F26: 0.12 | G26: 176.36 | H26: 52.4 | I26: 2297.25 | J26: 21.88 | K26: 29.8 | L26: 653.73 | M26: 0.01 | N26: 56.47 | O26: 20.68 | P26: 35.56 | Q26: 99.69 | R26: 7.45 | S26: 163.27
A27: 26 | B27: Olectra Greentec | C27: 1327.3 | D27: 78.47 | E27: 10898.01 | F27: 0.03 | G27: 20.68 | H27: 50.84 | I27: 448.92 | J27: 55.44 | K27: 20.39 | L27: 16.92 | M27: 0.24 | N27: 4.67 | O27: 14.15 | P27: 44.82 | Q27: 55.48 | R27: 10.38 | S27: 33.34
A28: 27 | B28: Mercury EV-Tech | C28: 50.97 | D28: 122.41 | E28: 968.29 | F28: 0 | G28: 1.55 | H28: 573.91 | I28: 30.68 | J28: 450.81 | K28: 5.15 | L28: 0.42 | M28: 0.02 | N28: 12.44 | O28: 4.42 | P28: 323.52 | Q28: 225.2 | R28: 3.5 | S28: 168.55
A29: 28 | B29: Bajaj Auto | C29: 8288.5 | D29: 9.45 | E29: 31.7 | F29: 231535.74 | G29: 2.53 | H29: 1801.85 | I29: -10.42 | J29: 12646.32 | K29: 28.06 | L29: 262.29 | M29: 0.27 | N29: 27.21 | O29: 22.77 | P29: 15.44 | Q29: 10.38 | R29: 6.58 | S29: 27.26
